CHANGES.txt
LICENSE
MANIFEST.in
README.rst
exampleconf.py
setup.cfg
setup.py
celery_redbeat_sempr.egg-info/PKG-INFO
celery_redbeat_sempr.egg-info/SOURCES.txt
celery_redbeat_sempr.egg-info/dependency_links.txt
celery_redbeat_sempr.egg-info/requires.txt
celery_redbeat_sempr.egg-info/top_level.txt
redbeat/__init__.py
redbeat/decoder.py
redbeat/schedulers.py
redbeat/schedules.py