Metadata-Version: 1.1
Name: celery-redbeat-sempr
Version: 0.11.1
Summary: A Celery Beat Scheduler using Redis for persistent storage
Home-page: https://github.com/sibson/redbeat
Author: Marc Sibson
Author-email: sibson+redbeat@gmail.com
License: Apache License, Version 2.0
Keywords: python,celery,beat,redis
Platform: UNKNOWN
Classifier: Development Status :: 5 - Production/Stable
Classifier: License :: OSI Approved :: Apache Software License
Classifier: Topic :: System :: Distributed Computing
Classifier: Topic :: Software Development :: Object Brokering
Classifier: Programming Language :: Python
Classifier: Programming Language :: Python :: 2
Classifier: Programming Language :: Python :: 2.7
Classifier: Programming Language :: Python :: 3
Classifier: Programming Language :: Python :: 3.4
Classifier: Programming Language :: Python :: 3.5
Classifier: Programming Language :: Python :: Implementation :: CPython
Classifier: Operating System :: OS Independent
